moviepy/Clip.py
moviepy/Effect.py
moviepy/__init__.py
moviepy/config.py
moviepy/decorators.py
moviepy/tools.py
moviepy/version.py
moviepy/audio/AudioClip.py
moviepy/audio/__init__.py
moviepy/audio/fx/AudioDelay.py
moviepy/audio/fx/AudioFadeIn.py
moviepy/audio/fx/AudioFadeOut.py
moviepy/audio/fx/AudioLoop.py
moviepy/audio/fx/AudioNormalize.py
moviepy/audio/fx/MultiplyStereoVolume.py
moviepy/audio/fx/MultiplyVolume.py
moviepy/audio/fx/__init__.py
moviepy/audio/io/AudioFileClip.py
moviepy/audio/io/__init__.py
moviepy/audio/io/ffmpeg_audiowriter.py
moviepy/audio/io/ffplay_audiopreviewer.py
moviepy/audio/io/readers.py
moviepy/audio/tools/__init__.py
moviepy/audio/tools/cuts.py
moviepy/video/VideoClip.py
moviepy/video/__init__.py
moviepy/video/compositing/CompositeVideoClip.py
moviepy/video/compositing/__init__.py
moviepy/video/fx/AccelDecel.py
moviepy/video/fx/BlackAndWhite.py
moviepy/video/fx/Blink.py
moviepy/video/fx/Crop.py
moviepy/video/fx/CrossFadeIn.py
moviepy/video/fx/CrossFadeOut.py
moviepy/video/fx/EvenSize.py
moviepy/video/fx/FadeIn.py
moviepy/video/fx/FadeOut.py
moviepy/video/fx/Freeze.py
moviepy/video/fx/FreezeRegion.py
moviepy/video/fx/GammaCorrection.py
moviepy/video/fx/HeadBlur.py
moviepy/video/fx/InvertColors.py
moviepy/video/fx/Loop.py
moviepy/video/fx/LumContrast.py
moviepy/video/fx/MakeLoopable.py
moviepy/video/fx/Margin.py
moviepy/video/fx/MaskColor.py
moviepy/video/fx/MasksAnd.py
moviepy/video/fx/MasksOr.py
moviepy/video/fx/MirrorX.py
moviepy/video/fx/MirrorY.py
moviepy/video/fx/MultiplyColor.py
moviepy/video/fx/MultiplySpeed.py
moviepy/video/fx/Painting.py
moviepy/video/fx/Resize.py
moviepy/video/fx/Rotate.py
moviepy/video/fx/Scroll.py
moviepy/video/fx/SlideIn.py
moviepy/video/fx/SlideOut.py
moviepy/video/fx/SuperSample.py
moviepy/video/fx/TimeMirror.py
moviepy/video/fx/TimeSymmetrize.py
moviepy/video/fx/__init__.py
moviepy/video/io/ImageSequenceClip.py
moviepy/video/io/VideoFileClip.py
moviepy/video/io/__init__.py
moviepy-2.2.0.dist-info/licenses/LICENCE.txt
moviepy-2.2.0.dist-info/METADATA
moviepy-2.2.0.dist-info/WHEEL
moviepy-2.2.0.dist-info/top_level.txt
moviepy-2.2.0.dist-info/RECORD
