Metadata-Version: 2.4
Name: moviepy
Version: 2.2.0
Summary: Video editing with Python
Author: Zulko 2024
License: MIT License
Keywords: video,editing,audio,compositing,ffmpeg
Classifier: Development Status :: 5 - Production/Stable
Classifier: Intended Audience :: Developers
Classifier: Natural Language :: English
Classifier: License :: OSI Approved :: MIT License
Classifier: Programming Language :: Python
Classifier: Programming Language :: Python :: 3.9
Classifier: Programming Language :: Python :: 3.10
Classifier: Programming Language :: Python :: 3.11
Classifier: Topic :: Multimedia
Classifier: Topic :: Multimedia :: Sound/Audio
Classifier: Topic :: Multimedia :: Sound/Audio :: Analysis
Classifier: Topic :: Multimedia :: Video
Classifier: Topic :: Multimedia :: Video :: Capture
Classifier: Topic :: Multimedia :: Video :: Conversion
License-File: LICENCE.txt
Requires-Dist: decorator<6.0,>=4.0.2
Requires-Dist: imageio<3.0,>=2.5
Requires-Dist: imageio_ffmpeg>=0.2.0
Requires-Dist: numpy>=1.25.0
Requires-Dist: proglog<=1.0.0
Requires-Dist: python-dotenv>=0.10
Requires-Dist: pillow<12.0,>=9.2.0
Provides-Extra: doc
Requires-Dist: numpydoc<2.0; extra == "doc"
Requires-Dist: Sphinx==6.*; extra == "doc"
Requires-Dist: pydata-sphinx-theme==0.13; extra == "doc"
Requires-Dist: sphinx_design; extra == "doc"
Provides-Extra: test
Requires-Dist: coveralls<4.0,>=3.0; extra == "test"
Requires-Dist: pytest-cov<3.0,>=2.5.1; extra == "test"
Requires-Dist: pytest<7.0.0,>=3.0.0; extra == "test"
Provides-Extra: lint
Requires-Dist: black>=23.7.0; extra == "lint"
Requires-Dist: flake8>=6.0.0; extra == "lint"
Requires-Dist: flake8-absolute-import>=1.0; extra == "lint"
Requires-Dist: flake8-docstrings>=1.7.0; extra == "lint"
Requires-Dist: flake8-rst-docstrings>=0.3; extra == "lint"
Requires-Dist: flake8-implicit-str-concat==0.4.0; extra == "lint"
Requires-Dist: isort>=5.12; extra == "lint"
Requires-Dist: pre-commit>=3.3; extra == "lint"
Dynamic: license-file
